opus/__init__.py
opus/cli.py
opus/execution.py
opus/opus_logging.py
opus/clouds/__init__.py
opus/clouds/cloud.py
opus/clouds/cloud_providers.py
opus/clouds/slurm.py
opus/common_types/__init__.py
opus/common_types/common.py
opus/frameworks/__init__.py
opus/frameworks/framework_types.py
opus/frameworks/frameworks.py
opus/frameworks/ray.py
opus/jobs/__init__.py
opus/jobs/job.py
opus/templates/slurm-ray-template.sh.j2
opus/utils/__init__.py
opus/utils/common_utils.py
opus/utils/db_utils.py
opus/utils/schema_utils.py
opus/utils/validator_utils.py
opus_pjlab-0.0.1.dist-info/LICENSE
opus_pjlab-0.0.1.dist-info/METADATA
opus_pjlab-0.0.1.dist-info/WHEEL
opus_pjlab-0.0.1.dist-info/entry_points.txt
opus_pjlab-0.0.1.dist-info/top_level.txt
opus_pjlab-0.0.1.dist-info/RECORD
