Metadata-Version: 2.1
Name: opus-pjlab
Version: 0.0.1
Summary: Opus: An auto-launcher for ray clusters on clouds
Author: AST
License: Apache 2.0
License-File: LICENSE
Requires-Dist: wheel
Requires-Dist: click >=7.0
Requires-Dist: pytest
Requires-Dist: prettytable
Requires-Dist: schema ==0.7.5
Requires-Dist: jinja2
Requires-Dist: pyyaml !=5.4.*,>3.13
Requires-Dist: ray[default]
Requires-Dist: pydantic
Requires-Dist: pendulum
Requires-Dist: requests
Requires-Dist: paramiko
